jio_sonar/__init__.py
jio_sonar/gaia_arguments.py
jio_sonar/runner.py
jio_sonar/version.py
jio_sonar/device/__init__.py
jio_sonar/device/adb.py
jio_sonar/device/adb_b2g.py
jio_sonar/device/adbmanager.py
jio_sonar/device/errors.py
jio_sonar/device/version.py
jio_sonar/logi/__init__.py
jio_sonar/logi/commandline.py
jio_sonar/logi/logtypes.py
jio_sonar/logi/reader.py
jio_sonar/logi/structuredlog.py
jio_sonar/logi/unstructuredlog.py
jio_sonar/logi/formatters/__init__.py
jio_sonar/logi/formatters/base.py
jio_sonar/logi/formatters/machformatter.py
jio_sonar/logi/formatters/process.py
jio_sonar/logi/formatters/tbplformatter.py
jio_sonar/logi/formatters/unittest.py
jio_sonar/logi/formatters/xunit.py
jio_sonar/logi/formatters/html/__init__.py
jio_sonar/logi/formatters/html/html.py
jio_sonar/logi/formatters/html/xmlgen.py
jio_sonar/logi/handlers/__init__.py
jio_sonar/logi/handlers/base.py
jio_sonar/logi/handlers/bufferhandler.py
jio_sonar/marionette_client/__init__.py
jio_sonar/marionette_client/addons.py
jio_sonar/marionette_client/by.py
jio_sonar/marionette_client/date_time_value.py
jio_sonar/marionette_client/decorators.py
jio_sonar/marionette_client/errors.py
jio_sonar/marionette_client/expected.py
jio_sonar/marionette_client/geckoinstance.py
jio_sonar/marionette_client/httpd.py
jio_sonar/marionette_client/keys.py
jio_sonar/marionette_client/localization.py
jio_sonar/marionette_client/marionette.py
jio_sonar/marionette_client/timeout.py
jio_sonar/marionette_client/transport.py
jio_sonar/marionette_client/wait.py
jio_sonar/mozprocess/__init__.py
jio_sonar/mozprocess/processhandler.py
jio_sonar/mozprocess/qijo.py
jio_sonar/mozprocess/winprocess.py
jio_sonar/test/__init__.py
jio_sonar/test/case.py
jio_sonar/test/results.py
jio_sonar-3.6.0.dist-info/DESCRIPTION.rst
jio_sonar-3.6.0.dist-info/METADATA
jio_sonar-3.6.0.dist-info/RECORD
jio_sonar-3.6.0.dist-info/WHEEL
jio_sonar-3.6.0.dist-info/metadata.json
jio_sonar-3.6.0.dist-info/top_level.txt
